modelslab_py/__init__.py
modelslab_py/core/__init__.py
modelslab_py/core/apis/__init__.py
modelslab_py/core/apis/audio.py
modelslab_py/core/apis/base.py
modelslab_py/core/apis/community.py
modelslab_py/core/apis/deepfake.py
modelslab_py/core/apis/image_editing.py
modelslab_py/core/apis/interior.py
modelslab_py/core/apis/realtime.py
modelslab_py/core/apis/three_d.py
modelslab_py/core/apis/video.py
modelslab_py/core/client.py
modelslab_py/core/response.py
modelslab_py/providers/__init__.py
modelslab_py/providers/alibaba/__init__.py
modelslab_py/providers/alibaba/api.py
modelslab_py/providers/alibaba/schemas.py
modelslab_py/providers/byteplus/__init__.py
modelslab_py/providers/byteplus/api.py
modelslab_py/providers/byteplus/schemas.py
modelslab_py/providers/elevenlabs/__init__.py
modelslab_py/providers/elevenlabs/api.py
modelslab_py/providers/elevenlabs/schemas.py
modelslab_py/providers/google/__init__.py
modelslab_py/providers/google/api.py
modelslab_py/providers/google/schemas.py
modelslab_py/providers/inworld/__init__.py
modelslab_py/providers/inworld/api.py
modelslab_py/providers/inworld/schemas.py
modelslab_py/providers/openai/__init__.py
modelslab_py/providers/openai/api.py
modelslab_py/providers/openai/schemas.py
modelslab_py/providers/runway/__init__.py
modelslab_py/providers/runway/api.py
modelslab_py/providers/runway/schemas.py
modelslab_py/providers/sonauto/__init__.py
modelslab_py/providers/sonauto/api.py
modelslab_py/providers/sonauto/schemas.py
modelslab_py/schemas/audio.py
modelslab_py/schemas/base.py
modelslab_py/schemas/community.py
modelslab_py/schemas/deepfake.py
modelslab_py/schemas/dreambooth.py
modelslab_py/schemas/image_editing.py
modelslab_py/schemas/interior.py
modelslab_py/schemas/realtime.py
modelslab_py/schemas/threed.py
modelslab_py/schemas/video.py
modelslab_py/utils/image_utils.py
modelslab_py-0.1.8.dist-info/METADATA
modelslab_py-0.1.8.dist-info/WHEEL
modelslab_py-0.1.8.dist-info/RECORD
