Metadata-Version: 2.4
Name: modelslab_py
Version: 0.1.8
Summary: ModelsLab's Official Python SDK
Author: Tanmay Patil
Author-email: tanmaypatil3151@gmail.com
Requires-Python: >=3.9,<4.0
Classifier: Programming Language :: Python :: 3
Classifier: Programming Language :: Python :: 3.9
Classifier: Programming Language :: Python :: 3.10
Classifier: Programming Language :: Python :: 3.11
Classifier: Programming Language :: Python :: 3.12
Classifier: Programming Language :: Python :: 3.13
Classifier: Programming Language :: Python :: 3.14
Provides-Extra: async
Requires-Dist: aiohttp (>=3.9.0,<4.0.0) ; extra == "async"
Requires-Dist: pydantic (>=2.11.3,<3.0.0)
